{
  "name": "TaxAuthority",
  "fields": [
    {
      "fieldName": "name",
      "fieldType": "String",
      "fieldValidateRules": ["unique", "maxlength"],
      "fieldValidateRulesMaxlength": "25"
    }
  ],
  "relationships": [],
  "changelogDate": "20220805153649",
  "entityTableName": "tax_authority",
  "dto": "no",
  "pagination": "no",
  "service": "no",
  "jpaMetamodelFiltering": false,
  "fluentMethods": true,
  "readOnly": false,
  "embedded": false,
  "clientRootFolder": "",
  "applications": ["hr"]
}
